jira/jira.py
jira/manifest.toml
jira/test_jira.py
opsbox_jira_output-0.1.5.dist-info/LICENCE.txt
opsbox_jira_output-0.1.5.dist-info/METADATA
opsbox_jira_output-0.1.5.dist-info/WHEEL
opsbox_jira_output-0.1.5.dist-info/entry_points.txt
opsbox_jira_output-0.1.5.dist-info/top_level.txt
opsbox_jira_output-0.1.5.dist-info/RECORD
